{
    "メディテレーニアンハーバー": {
        "ディズニーシー・トランジットスチーマーライン": {
            "Realtime": {
                "update_time": "（8:59更新）",
                "wait_time": "5",
                "operation": "運営中",
                "operation_time": "9:00 – 20:45",
                "operation_warning": "",
                "DPA": {
                    "use": false,
                    "stock": null
                },
                "PP": {
                    "use": false,
                    "stock": null
                },
                "SP": {
                    "use": false,
                    "stock": null
                }
            },
            "History": [
                {
                    "time": "09:00",
                    "update_time": "運営/公演予定",
                    "wait_time": "",
                    "operation": "",
                    "operation_time": "9:00 - 20:45",
                    "operation_warning": "",
                    "DPA": {
                        "use": false,
                        "stock": null
                    },
                    "PP": {
                        "use": false,
                        "stock": null
                    },
                    "SP": {
                        "use": false,
                        "stock": null
                    }
                },
                {
                    "time": "09:05",
                    "update_time": "（8:59更新）",
                    "wait_time": "5",
                    "operation": "運営中",
                    "operation_time": "9:00 – 20:45",
                    "operation_warning": "",
                    "DPA": {
                        "use": false,
                        "stock": null
                    },
                    "PP": {
                        "use": false,
                        "stock": null
                    },
                    "SP": {
                        "use": false,
                        "stock": null
                    }
                }
            ]
        },
        "ソアリン：ファンタスティック・フライト": {
            "Realtime": {
                "update_time": "（8:54更新）",
                "wait_time": "30",
                "operation": "運営中",
                "operation_time": "9:00 – 21:00",
                "operation_warning": "ディズニー・プレミアアクセス販売中",
                "DPA": {
                    "use": true,
                    "stock": true
                },
                "PP": {
                    "use": false,
                    "stock": null
                },
                "SP": {
                    "use": false,
                    "stock": null
                }
            },
            "History": [
                {
                    "time": "09:00",
                    "update_time": "運営/公演予定",
                    "wait_time": "",
                    "operation": "",
                    "operation_time": "9:00 - 21:00",
                    "operation_warning": "",
                    "DPA": {
                        "use": true,
                        "stock": false
                    },
                    "PP": {
                        "use": false,
                        "stock": null
                    },
                    "SP": {
                        "use": false,
                        "stock": null
                    }
                },
                {
                    "time": "09:05",
                    "update_time": "（8:54更新）",
                    "wait_time": "30",
                    "operation": "運営中",
                    "operation_time": "9:00 – 21:00",
                    "operation_warning": "ディズニー・プレミアアクセス販売中",
                    "DPA": {
                        "use": true,
                        "stock": true
                    },
                    "PP": {
                        "use": false,
                        "stock": null
                    },
                    "SP": {
                        "use": false,
                        "stock": null
                    }
                }
            ]
        },
        "フォートレス・エクスプロレーション": {
            "Realtime": {
                "update_time": "（9:00更新）",
                "wait_time": "",
                "operation": "運営中",
                "operation_time": "9:00 – 21:00",
                "operation_warning": "",
                "DPA": {
                    "use": false,
                    "stock": null
                },
                "PP": {
                    "use": false,
                    "stock": null
                },
                "SP": {
                    "use": false,
                    "stock": null
                }
            },
            "History": [
                {
                    "time": "09:00",
                    "update_time": "運営/公演予定",
                    "wait_time": "",
                    "operation": "",
                    "operation_time": "9:00 - 21:00",
                    "operation_warning": "",
                    "DPA": {
                        "use": false,
                        "stock": null
                    },
                    "PP": {
                        "use": false,
                        "stock": null
                    },
                    "SP": {
                        "use": false,
                        "stock": null
                    }
                },
                {
                    "time": "09:05",
                    "update_time": "（9:00更新）",
                    "wait_time": "",
                    "operation": "運営中",
                    "operation_time": "9:00 – 21:00",
                    "operation_warning": "",
                    "DPA": {
                        "use": false,
                        "stock": null
                    },
                    "PP": {
                        "use": false,
                        "stock": null
                    },
                    "SP": {
                        "use": false,
                        "stock": null
                    }
                }
            ]
        },
        "ヴェネツィアン・ゴンドラ": {
            "Realtime": {
                "update_time": "（9:00更新）",
                "wait_time": "5",
                "operation": "運営中",
                "operation_time": "9:00 – 21:00",
                "operation_warning": "",
                "DPA": {
                    "use": false,
                    "stock": null
                },
                "PP": {
                    "use": false,
                    "stock": null
                },
                "SP": {
                    "use": false,
                    "stock": null
                }
            },
            "History": [
                {
                    "time": "09:00",
                    "update_time": "運営/公演予定",
                    "wait_time": "",
                    "operation": "",
                    "operation_time": "9:00 - 21:00",
                    "operation_warning": "",
                    "DPA": {
                        "use": false,
                        "stock": null
                    },
                    "PP": {
                        "use": false,
                        "stock": null
                    },
                    "SP": {
                        "use": false,
                        "stock": null
                    }
                },
                {
                    "time": "09:05",
                    "update_time": "（9:00更新）",
                    "wait_time": "5",
                    "operation": "運営中",
                    "operation_time": "9:00 – 21:00",
                    "operation_warning": "",
                    "DPA": {
                        "use": false,
                        "stock": null
                    },
                    "PP": {
                        "use": false,
                        "stock": null
                    },
                    "SP": {
                        "use": false,
                        "stock": null
                    }
                }
            ]
        },
        "フォートレス・エクスプロレーション\"ザ・レオナルドチャレンジ\"": {
            "Realtime": {
                "update_time": "（9:00更新）",
                "wait_time": "",
                "operation": "準備中",
                "operation_time": "12:00 – 18:00",
                "operation_warning": "",
                "DPA": {
                    "use": false,
                    "stock": null
                },
                "PP": {
                    "use": false,
                    "stock": null
                },
                "SP": {
                    "use": false,
                    "stock": null
                }
            },
            "History": [
                {
                    "time": "09:00",
                    "update_time": "運営/公演予定",
                    "wait_time": "",
                    "operation": "",
                    "operation_time": "12:00 - 18:00",
                    "operation_warning": "",
                    "DPA": {
                        "use": false,
                        "stock": null
                    },
                    "PP": {
                        "use": false,
                        "stock": null
                    },
                    "SP": {
                        "use": false,
                        "stock": null
                    }
                },
                {
                    "time": "09:05",
                    "update_time": "（9:00更新）",
                    "wait_time": "",
                    "operation": "準備中",
                    "operation_time": "12:00 – 18:00",
                    "operation_warning": "",
                    "DPA": {
                        "use": false,
                        "stock": null
                    },
                    "PP": {
                        "use": false,
                        "stock": null
                    },
                    "SP": {
                        "use": false,
                        "stock": null
                    }
                }
            ]
        }
    },
    "アメリカンウォーターフロント": {
        "タートル・トーク": {
            "Realtime": {
                "update_time": "（9:00更新）",
                "wait_time": "5",
                "operation": "運営中",
                "operation_time": "9:00 – 21:00",
                "operation_warning": "40周年記念プライオリティパス発行中",
                "DPA": {
                    "use": false,
                    "stock": null
                },
                "PP": {
                    "use": true,
                    "stock": true
                },
                "SP": {
                    "use": false,
                    "stock": null
                }
            },
            "History": [
                {
                    "time": "09:00",
                    "update_time": "運営/公演予定",
                    "wait_time": "",
                    "operation": "",
                    "operation_time": "9:00 - 21:00",
                    "operation_warning": "",
                    "DPA": {
                        "use": false,
                        "stock": null
                    },
                    "PP": {
                        "use": true,
                        "stock": false
                    },
                    "SP": {
                        "use": false,
                        "stock": null
                    }
                },
                {
                    "time": "09:05",
                    "update_time": "（9:00更新）",
                    "wait_time": "5",
                    "operation": "運営中",
                    "operation_time": "9:00 – 21:00",
                    "operation_warning": "40周年記念プライオリティパス発行中",
                    "DPA": {
                        "use": false,
                        "stock": null
                    },
                    "PP": {
                        "use": true,
                        "stock": true
                    },
                    "SP": {
                        "use": false,
                        "stock": null
                    }
                }
            ]
        },
        "タワー・オブ・テラー": {
            "Realtime": {
                "update_time": "（9:00更新）",
                "wait_time": "10",
                "operation": "運営中",
                "operation_time": "9:00 – 21:00",
                "operation_warning": "ディズニー・プレミアアクセス販売中",
                "DPA": {
                    "use": true,
                    "stock": true
                },
                "PP": {
                    "use": false,
                    "stock": null
                },
                "SP": {
                    "use": false,
                    "stock": null
                }
            },
            "History": [
                {
                    "time": "09:00",
                    "update_time": "運営/公演予定",
                    "wait_time": "",
                    "operation": "",
                    "operation_time": "9:00 - 21:00",
                    "operation_warning": "",
                    "DPA": {
                        "use": true,
                        "stock": false
                    },
                    "PP": {
                        "use": false,
                        "stock": null
                    },
                    "SP": {
                        "use": false,
                        "stock": null
                    }
                },
                {
                    "time": "09:05",
                    "update_time": "（9:00更新）",
                    "wait_time": "10",
                    "operation": "運営中",
                    "operation_time": "9:00 – 21:00",
                    "operation_warning": "ディズニー・プレミアアクセス販売中",
                    "DPA": {
                        "use": true,
                        "stock": true
                    },
                    "PP": {
                        "use": false,
                        "stock": null
                    },
                    "SP": {
                        "use": false,
                        "stock": null
                    }
                }
            ]
        },
        "ディズニーシー・エレクトリックレールウェイ": {
            "Realtime": {
                "update_time": "（9:01更新）",
                "wait_time": "5",
                "operation": "運営中",
                "operation_time": "9:00 – 21:00",
                "operation_warning": "",
                "DPA": {
                    "use": false,
                    "stock": null
                },
                "PP": {
                    "use": false,
                    "stock": null
                },
                "SP": {
                    "use": false,
                    "stock": null
                }
            },
            "History": [
                {
                    "time": "09:00",
                    "update_time": "運営/公演予定",
                    "wait_time": "",
                    "operation": "",
                    "operation_time": "9:00 - 21:00",
                    "operation_warning": "",
                    "DPA": {
                        "use": false,
                        "stock": null
                    },
                    "PP": {
                        "use": false,
                        "stock": null
                    },
                    "SP": {
                        "use": false,
                        "stock": null
                    }
                },
                {
                    "time": "09:05",
                    "update_time": "（9:01更新）",
                    "wait_time": "5",
                    "operation": "運営中",
                    "operation_time": "9:00 – 21:00",
                    "operation_warning": "",
                    "DPA": {
                        "use": false,
                        "stock": null
                    },
                    "PP": {
                        "use": false,
                        "stock": null
                    },
                    "SP": {
                        "use": false,
                        "stock": null
                    }
                }
            ]
        },
        "ディズニーシー・トランジットスチーマーライン": {
            "Realtime": {
                "update_time": "（9:00更新）",
                "wait_time": "",
                "operation": "準備中",
                "operation_time": "11:00 – 17:40",
                "operation_warning": "",
                "DPA": {
                    "use": false,
                    "stock": null
                },
                "PP": {
                    "use": false,
                    "stock": null
                },
                "SP": {
                    "use": false,
                    "stock": null
                }
            },
            "History": [
                {
                    "time": "09:00",
                    "update_time": "運営/公演予定",
                    "wait_time": "",
                    "operation": "",
                    "operation_time": "11:00 - 17:40",
                    "operation_warning": "",
                    "DPA": {
                        "use": false,
                        "stock": null
                    },
                    "PP": {
                        "use": false,
                        "stock": null
                    },
                    "SP": {
                        "use": false,
                        "stock": null
                    }
                },
                {
                    "time": "09:05",
                    "update_time": "（9:00更新）",
                    "wait_time": "",
                    "operation": "準備中",
                    "operation_time": "11:00 – 17:40",
                    "operation_warning": "",
                    "DPA": {
                        "use": false,
                        "stock": null
                    },
                    "PP": {
                        "use": false,
                        "stock": null
                    },
                    "SP": {
                        "use": false,
                        "stock": null
                    }
                }
            ]
        },
        "トイ・ストーリー・マニア！": {
            "Realtime": {
                "update_time": "（8:57更新）",
                "wait_time": "15",
                "operation": "運営中",
                "operation_time": "9:00 – 21:00",
                "operation_warning": "ディズニー・プレミアアクセス販売中",
                "DPA": {
                    "use": true,
                    "stock": true
                },
                "PP": {
                    "use": false,
                    "stock": null
                },
                "SP": {
                    "use": false,
                    "stock": null
                }
            },
            "History": [
                {
                    "time": "09:00",
                    "update_time": "運営/公演予定",
                    "wait_time": "",
                    "operation": "",
                    "operation_time": "9:00 - 21:00",
                    "operation_warning": "",
                    "DPA": {
                        "use": true,
                        "stock": false
                    },
                    "PP": {
                        "use": false,
                        "stock": null
                    },
                    "SP": {
                        "use": false,
                        "stock": null
                    }
                },
                {
                    "time": "09:05",
                    "update_time": "（8:57更新）",
                    "wait_time": "15",
                    "operation": "運営中",
                    "operation_time": "9:00 – 21:00",
                    "operation_warning": "ディズニー・プレミアアクセス販売中",
                    "DPA": {
                        "use": true,
                        "stock": true
                    },
                    "PP": {
                        "use": false,
                        "stock": null
                    },
                    "SP": {
                        "use": false,
                        "stock": null
                    }
                }
            ]
        },
        "ビッグシティ・ヴィークル": {
            "Realtime": {
                "update_time": "（9:00更新）",
                "wait_time": "",
                "operation": "準備中",
                "operation_time": "13:00 – 19:00",
                "operation_warning": "",
                "DPA": {
                    "use": false,
                    "stock": null
                },
                "PP": {
                    "use": false,
                    "stock": null
                },
                "SP": {
                    "use": false,
                    "stock": null
                }
            },
            "History": [
                {
                    "time": "09:00",
                    "update_time": "運営/公演予定",
                    "wait_time": "",
                    "operation": "",
                    "operation_time": "13:00 - 19:00",
                    "operation_warning": "",
                    "DPA": {
                        "use": false,
                        "stock": null
                    },
                    "PP": {
                        "use": false,
                        "stock": null
                    },
                    "SP": {
                        "use": false,
                        "stock": null
                    }
                },
                {
                    "time": "09:05",
                    "update_time": "（9:00更新）",
                    "wait_time": "",
                    "operation": "準備中",
                    "operation_time": "13:00 – 19:00",
                    "operation_warning": "",
                    "DPA": {
                        "use": false,
                        "stock": null
                    },
                    "PP": {
                        "use": false,
                        "stock": null
                    },
                    "SP": {
                        "use": false,
                        "stock": null
                    }
                }
            ]
        }
    },
    "ポートディスカバリー": {
        "アクアトピア": {
            "Realtime": {
                "update_time": "（9:00更新）",
                "wait_time": "5",
                "operation": "運営中",
                "operation_time": "9:00 – 21:00",
                "operation_warning": "",
                "DPA": {
                    "use": false,
                    "stock": null
                },
                "PP": {
                    "use": false,
                    "stock": null
                },
                "SP": {
                    "use": false,
                    "stock": null
                }
            },
            "History": [
                {
                    "time": "09:00",
                    "update_time": "運営/公演予定",
                    "wait_time": "",
                    "operation": "",
                    "operation_time": "9:00 - 21:00",
                    "operation_warning": "",
                    "DPA": {
                        "use": false,
                        "stock": null
                    },
                    "PP": {
                        "use": false,
                        "stock": null
                    },
                    "SP": {
                        "use": false,
                        "stock": null
                    }
                },
                {
                    "time": "09:05",
                    "update_time": "（9:00更新）",
                    "wait_time": "5",
                    "operation": "運営中",
                    "operation_time": "9:00 – 21:00",
                    "operation_warning": "",
                    "DPA": {
                        "use": false,
                        "stock": null
                    },
                    "PP": {
                        "use": false,
                        "stock": null
                    },
                    "SP": {
                        "use": false,
                        "stock": null
                    }
                }
            ]
        },
        "ディズニーシー・エレクトリックレールウェイ": {
            "Realtime": {
                "update_time": "（9:00更新）",
                "wait_time": "5",
                "operation": "運営中",
                "operation_time": "9:00 – 21:00",
                "operation_warning": "",
                "DPA": {
                    "use": false,
                    "stock": null
                },
                "PP": {
                    "use": false,
                    "stock": null
                },
                "SP": {
                    "use": false,
                    "stock": null
                }
            },
            "History": [
                {
                    "time": "09:00",
                    "update_time": "運営/公演予定",
                    "wait_time": "",
                    "operation": "",
                    "operation_time": "9:00 - 21:00",
                    "operation_warning": "",
                    "DPA": {
                        "use": false,
                        "stock": null
                    },
                    "PP": {
                        "use": false,
                        "stock": null
                    },
                    "SP": {
                        "use": false,
                        "stock": null
                    }
                },
                {
                    "time": "09:05",
                    "update_time": "（9:00更新）",
                    "wait_time": "5",
                    "operation": "運営中",
                    "operation_time": "9:00 – 21:00",
                    "operation_warning": "",
                    "DPA": {
                        "use": false,
                        "stock": null
                    },
                    "PP": {
                        "use": false,
                        "stock": null
                    },
                    "SP": {
                        "use": false,
                        "stock": null
                    }
                }
            ]
        },
        "ニモ＆フレンズ・シーライダー": {
            "Realtime": {
                "update_time": "（7:52更新）",
                "wait_time": "15",
                "operation": "運営中",
                "operation_time": "9:00 – 21:00",
                "operation_warning": "40周年記念プライオリティパス発行中",
                "DPA": {
                    "use": false,
                    "stock": null
                },
                "PP": {
                    "use": true,
                    "stock": true
                },
                "SP": {
                    "use": false,
                    "stock": null
                }
            },
            "History": [
                {
                    "time": "09:00",
                    "update_time": "運営/公演予定",
                    "wait_time": "",
                    "operation": "",
                    "operation_time": "9:00 - 21:00",
                    "operation_warning": "",
                    "DPA": {
                        "use": false,
                        "stock": null
                    },
                    "PP": {
                        "use": true,
                        "stock": false
                    },
                    "SP": {
                        "use": false,
                        "stock": null
                    }
                },
                {
                    "time": "09:05",
                    "update_time": "（7:52更新）",
                    "wait_time": "15",
                    "operation": "運営中",
                    "operation_time": "9:00 – 21:00",
                    "operation_warning": "40周年記念プライオリティパス発行中",
                    "DPA": {
                        "use": false,
                        "stock": null
                    },
                    "PP": {
                        "use": true,
                        "stock": true
                    },
                    "SP": {
                        "use": false,
                        "stock": null
                    }
                }
            ]
        }
    },
    "ロストリバーデルタ": {
        "インディ・ジョーンズ®・アドベンチャー： クリスタルスカルの魔宮": {
            "Realtime": {
                "update_time": "（9:00更新）",
                "wait_time": "5",
                "operation": "運営中",
                "operation_time": "9:00 – 21:00",
                "operation_warning": "40周年記念プライオリティパス発行中",
                "DPA": {
                    "use": false,
                    "stock": null
                },
                "PP": {
                    "use": true,
                    "stock": true
                },
                "SP": {
                    "use": false,
                    "stock": null
                }
            },
            "History": [
                {
                    "time": "09:00",
                    "update_time": "運営/公演予定",
                    "wait_time": "",
                    "operation": "",
                    "operation_time": "9:00 - 21:00",
                    "operation_warning": "",
                    "DPA": {
                        "use": false,
                        "stock": null
                    },
                    "PP": {
                        "use": true,
                        "stock": false
                    },
                    "SP": {
                        "use": false,
                        "stock": null
                    }
                },
                {
                    "time": "09:05",
                    "update_time": "（9:00更新）",
                    "wait_time": "5",
                    "operation": "運営中",
                    "operation_time": "9:00 – 21:00",
                    "operation_warning": "40周年記念プライオリティパス発行中",
                    "DPA": {
                        "use": false,
                        "stock": null
                    },
                    "PP": {
                        "use": true,
                        "stock": true
                    },
                    "SP": {
                        "use": false,
                        "stock": null
                    }
                }
            ]
        },
        "ディズニーシー・トランジットスチーマーライン": {
            "Realtime": {
                "update_time": "（9:00更新）",
                "wait_time": "5",
                "operation": "運営中",
                "operation_time": "9:00 – 21:00",
                "operation_warning": "",
                "DPA": {
                    "use": false,
                    "stock": null
                },
                "PP": {
                    "use": false,
                    "stock": null
                },
                "SP": {
                    "use": false,
                    "stock": null
                }
            },
            "History": [
                {
                    "time": "09:00",
                    "update_time": "運営/公演予定",
                    "wait_time": "",
                    "operation": "",
                    "operation_time": "9:00 - 21:00",
                    "operation_warning": "",
                    "DPA": {
                        "use": false,
                        "stock": null
                    },
                    "PP": {
                        "use": false,
                        "stock": null
                    },
                    "SP": {
                        "use": false,
                        "stock": null
                    }
                },
                {
                    "time": "09:05",
                    "update_time": "（9:00更新）",
                    "wait_time": "5",
                    "operation": "運営中",
                    "operation_time": "9:00 – 21:00",
                    "operation_warning": "",
                    "DPA": {
                        "use": false,
                        "stock": null
                    },
                    "PP": {
                        "use": false,
                        "stock": null
                    },
                    "SP": {
                        "use": false,
                        "stock": null
                    }
                }
            ]
        },
        "レイジングスピリッツ": {
            "Realtime": {
                "update_time": "（9:00更新）",
                "wait_time": "5",
                "operation": "運営中",
                "operation_time": "9:00 – 21:00",
                "operation_warning": "40周年記念プライオリティパス発行中",
                "DPA": {
                    "use": false,
                    "stock": null
                },
                "PP": {
                    "use": true,
                    "stock": true
                },
                "SP": {
                    "use": false,
                    "stock": null
                }
            },
            "History": [
                {
                    "time": "09:00",
                    "update_time": "運営/公演予定",
                    "wait_time": "",
                    "operation": "",
                    "operation_time": "9:00 - 21:00",
                    "operation_warning": "",
                    "DPA": {
                        "use": false,
                        "stock": null
                    },
                    "PP": {
                        "use": true,
                        "stock": false
                    },
                    "SP": {
                        "use": false,
                        "stock": null
                    }
                },
                {
                    "time": "09:05",
                    "update_time": "（9:00更新）",
                    "wait_time": "5",
                    "operation": "運営中",
                    "operation_time": "9:00 – 21:00",
                    "operation_warning": "40周年記念プライオリティパス発行中",
                    "DPA": {
                        "use": false,
                        "stock": null
                    },
                    "PP": {
                        "use": true,
                        "stock": true
                    },
                    "SP": {
                        "use": false,
                        "stock": null
                    }
                }
            ]
        }
    },
    "ファンタジースプリングス": {
        "アナとエルサのフローズンジャーニー": {
            "Realtime": {
                "update_time": "（9:00更新）",
                "wait_time": "40",
                "operation": "運営中",
                "operation_time": "9:00 – 21:00",
                "operation_warning": "ディズニー・プレミアアクセス販売中",
                "DPA": {
                    "use": true,
                    "stock": true
                },
                "PP": {
                    "use": false,
                    "stock": null
                },
                "SP": {
                    "use": false,
                    "stock": null
                }
            },
            "History": [
                {
                    "time": "09:00",
                    "update_time": "運営/公演予定",
                    "wait_time": "",
                    "operation": "",
                    "operation_time": "9:00 - 21:00",
                    "operation_warning": "",
                    "DPA": {
                        "use": true,
                        "stock": false
                    },
                    "PP": {
                        "use": false,
                        "stock": null
                    },
                    "SP": {
                        "use": false,
                        "stock": null
                    }
                },
                {
                    "time": "09:05",
                    "update_time": "（9:00更新）",
                    "wait_time": "40",
                    "operation": "運営中",
                    "operation_time": "9:00 – 21:00",
                    "operation_warning": "ディズニー・プレミアアクセス販売中",
                    "DPA": {
                        "use": true,
                        "stock": true
                    },
                    "PP": {
                        "use": false,
                        "stock": null
                    },
                    "SP": {
                        "use": false,
                        "stock": null
                    }
                }
            ]
        },
        "ラプンツェルのランタンフェスティバル": {
            "Realtime": {
                "update_time": "（9:03更新）",
                "wait_time": "10",
                "operation": "運営中",
                "operation_time": "9:00 – 21:00",
                "operation_warning": "ディズニー・プレミアアクセス販売中",
                "DPA": {
                    "use": true,
                    "stock": true
                },
                "PP": {
                    "use": false,
                    "stock": null
                },
                "SP": {
                    "use": false,
                    "stock": null
                }
            },
            "History": [
                {
                    "time": "09:00",
                    "update_time": "運営/公演予定",
                    "wait_time": "",
                    "operation": "",
                    "operation_time": "9:00 - 21:00",
                    "operation_warning": "",
                    "DPA": {
                        "use": true,
                        "stock": false
                    },
                    "PP": {
                        "use": false,
                        "stock": null
                    },
                    "SP": {
                        "use": false,
                        "stock": null
                    }
                },
                {
                    "time": "09:05",
                    "update_time": "（9:03更新）",
                    "wait_time": "10",
                    "operation": "運営中",
                    "operation_time": "9:00 – 21:00",
                    "operation_warning": "ディズニー・プレミアアクセス販売中",
                    "DPA": {
                        "use": true,
                        "stock": true
                    },
                    "PP": {
                        "use": false,
                        "stock": null
                    },
                    "SP": {
                        "use": false,
                        "stock": null
                    }
                }
            ]
        },
        "ピーターパンのネバーランドアドベンチャー": {
            "Realtime": {
                "update_time": "（9:01更新）",
                "wait_time": "5",
                "operation": "運営中",
                "operation_time": "9:00 – 21:00",
                "operation_warning": "ディズニー・プレミアアクセス販売中",
                "DPA": {
                    "use": true,
                    "stock": true
                },
                "PP": {
                    "use": false,
                    "stock": null
                },
                "SP": {
                    "use": false,
                    "stock": null
                }
            },
            "History": [
                {
                    "time": "09:00",
                    "update_time": "運営/公演予定",
                    "wait_time": "",
                    "operation": "",
                    "operation_time": "9:00 - 21:00",
                    "operation_warning": "",
                    "DPA": {
                        "use": true,
                        "stock": false
                    },
                    "PP": {
                        "use": false,
                        "stock": null
                    },
                    "SP": {
                        "use": false,
                        "stock": null
                    }
                },
                {
                    "time": "09:05",
                    "update_time": "（9:01更新）",
                    "wait_time": "5",
                    "operation": "運営中",
                    "operation_time": "9:00 – 21:00",
                    "operation_warning": "ディズニー・プレミアアクセス販売中",
                    "DPA": {
                        "use": true,
                        "stock": true
                    },
                    "PP": {
                        "use": false,
                        "stock": null
                    },
                    "SP": {
                        "use": false,
                        "stock": null
                    }
                }
            ]
        },
        "フェアリー・ティンカーベルのビジーバギー": {
            "Realtime": {
                "update_time": "（8:56更新）",
                "wait_time": "5",
                "operation": "運営中",
                "operation_time": "9:00 – 21:00",
                "operation_warning": "",
                "DPA": {
                    "use": false,
                    "stock": null
                },
                "PP": {
                    "use": false,
                    "stock": null
                },
                "SP": {
                    "use": false,
                    "stock": null
                }
            },
            "History": [
                {
                    "time": "09:00",
                    "update_time": "運営/公演予定",
                    "wait_time": "",
                    "operation": "",
                    "operation_time": "9:00 - 21:00",
                    "operation_warning": "",
                    "DPA": {
                        "use": false,
                        "stock": null
                    },
                    "PP": {
                        "use": false,
                        "stock": null
                    },
                    "SP": {
                        "use": false,
                        "stock": null
                    }
                },
                {
                    "time": "09:05",
                    "update_time": "（8:56更新）",
                    "wait_time": "5",
                    "operation": "運営中",
                    "operation_time": "9:00 – 21:00",
                    "operation_warning": "",
                    "DPA": {
                        "use": false,
                        "stock": null
                    },
                    "PP": {
                        "use": false,
                        "stock": null
                    },
                    "SP": {
                        "use": false,
                        "stock": null
                    }
                }
            ]
        }
    },
    "アラビアンコースト": {
        "キャラバンカルーセル": {
            "Realtime": {
                "update_time": "（9:00更新）",
                "wait_time": "",
                "operation": "準備中",
                "operation_time": "10:00 – 21:00",
                "operation_warning": "",
                "DPA": {
                    "use": false,
                    "stock": null
                },
                "PP": {
                    "use": false,
                    "stock": null
                },
                "SP": {
                    "use": false,
                    "stock": null
                }
            },
            "History": [
                {
                    "time": "09:00",
                    "update_time": "運営/公演予定",
                    "wait_time": "",
                    "operation": "",
                    "operation_time": "10:00 - 21:00",
                    "operation_warning": "",
                    "DPA": {
                        "use": false,
                        "stock": null
                    },
                    "PP": {
                        "use": false,
                        "stock": null
                    },
                    "SP": {
                        "use": false,
                        "stock": null
                    }
                },
                {
                    "time": "09:05",
                    "update_time": "（9:00更新）",
                    "wait_time": "",
                    "operation": "準備中",
                    "operation_time": "10:00 – 21:00",
                    "operation_warning": "",
                    "DPA": {
                        "use": false,
                        "stock": null
                    },
                    "PP": {
                        "use": false,
                        "stock": null
                    },
                    "SP": {
                        "use": false,
                        "stock": null
                    }
                }
            ]
        },
        "ジャスミンのフライングカーペット": {
            "Realtime": {
                "update_time": "（9:00更新）",
                "wait_time": "5",
                "operation": "運営中",
                "operation_time": "9:00 – 21:00",
                "operation_warning": "",
                "DPA": {
                    "use": false,
                    "stock": null
                },
                "PP": {
                    "use": false,
                    "stock": null
                },
                "SP": {
                    "use": false,
                    "stock": null
                }
            },
            "History": [
                {
                    "time": "09:00",
                    "update_time": "運営/公演予定",
                    "wait_time": "",
                    "operation": "",
                    "operation_time": "9:00 - 21:00",
                    "operation_warning": "",
                    "DPA": {
                        "use": false,
                        "stock": null
                    },
                    "PP": {
                        "use": false,
                        "stock": null
                    },
                    "SP": {
                        "use": false,
                        "stock": null
                    }
                },
                {
                    "time": "09:05",
                    "update_time": "（9:00更新）",
                    "wait_time": "5",
                    "operation": "運営中",
                    "operation_time": "9:00 – 21:00",
                    "operation_warning": "",
                    "DPA": {
                        "use": false,
                        "stock": null
                    },
                    "PP": {
                        "use": false,
                        "stock": null
                    },
                    "SP": {
                        "use": false,
                        "stock": null
                    }
                }
            ]
        },
        "シンドバッド・ストーリーブック・ヴォヤッジ": {
            "Realtime": {
                "update_time": "（9:00更新）",
                "wait_time": "5",
                "operation": "運営中",
                "operation_time": "9:00 – 21:00",
                "operation_warning": "",
                "DPA": {
                    "use": false,
                    "stock": null
                },
                "PP": {
                    "use": false,
                    "stock": null
                },
                "SP": {
                    "use": false,
                    "stock": null
                }
            },
            "History": [
                {
                    "time": "09:00",
                    "update_time": "運営/公演予定",
                    "wait_time": "",
                    "operation": "",
                    "operation_time": "9:00 - 21:00",
                    "operation_warning": "",
                    "DPA": {
                        "use": false,
                        "stock": null
                    },
                    "PP": {
                        "use": false,
                        "stock": null
                    },
                    "SP": {
                        "use": false,
                        "stock": null
                    }
                },
                {
                    "time": "09:05",
                    "update_time": "（9:00更新）",
                    "wait_time": "5",
                    "operation": "運営中",
                    "operation_time": "9:00 – 21:00",
                    "operation_warning": "",
                    "DPA": {
                        "use": false,
                        "stock": null
                    },
                    "PP": {
                        "use": false,
                        "stock": null
                    },
                    "SP": {
                        "use": false,
                        "stock": null
                    }
                }
            ]
        },
        "マジックランプシアター": {
            "Realtime": {
                "update_time": "（9:00更新）",
                "wait_time": "",
                "operation": "準備中",
                "operation_time": "10:00 – 20:35",
                "operation_warning": "40周年記念プライオリティパス発行中",
                "DPA": {
                    "use": false,
                    "stock": null
                },
                "PP": {
                    "use": true,
                    "stock": true
                },
                "SP": {
                    "use": false,
                    "stock": null
                }
            },
            "History": [
                {
                    "time": "09:00",
                    "update_time": "運営/公演予定",
                    "wait_time": "",
                    "operation": "",
                    "operation_time": "10:00 - 20:35",
                    "operation_warning": "",
                    "DPA": {
                        "use": false,
                        "stock": null
                    },
                    "PP": {
                        "use": true,
                        "stock": false
                    },
                    "SP": {
                        "use": false,
                        "stock": null
                    }
                },
                {
                    "time": "09:05",
                    "update_time": "（9:00更新）",
                    "wait_time": "",
                    "operation": "準備中",
                    "operation_time": "10:00 – 20:35",
                    "operation_warning": "40周年記念プライオリティパス発行中",
                    "DPA": {
                        "use": false,
                        "stock": null
                    },
                    "PP": {
                        "use": true,
                        "stock": true
                    },
                    "SP": {
                        "use": false,
                        "stock": null
                    }
                }
            ]
        }
    },
    "マーメイドラグーン": {
        "アリエルのプレイグラウンド": {
            "Realtime": {
                "update_time": "（9:00更新）",
                "wait_time": "",
                "operation": "運営中",
                "operation_time": "9:00 – 21:00",
                "operation_warning": "",
                "DPA": {
                    "use": false,
                    "stock": null
                },
                "PP": {
                    "use": false,
                    "stock": null
                },
                "SP": {
                    "use": false,
                    "stock": null
                }
            },
            "History": [
                {
                    "time": "09:00",
                    "update_time": "運営/公演予定",
                    "wait_time": "",
                    "operation": "",
                    "operation_time": "9:00 - 21:00",
                    "operation_warning": "",
                    "DPA": {
                        "use": false,
                        "stock": null
                    },
                    "PP": {
                        "use": false,
                        "stock": null
                    },
                    "SP": {
                        "use": false,
                        "stock": null
                    }
                },
                {
                    "time": "09:05",
                    "update_time": "（9:00更新）",
                    "wait_time": "",
                    "operation": "運営中",
                    "operation_time": "9:00 – 21:00",
                    "operation_warning": "",
                    "DPA": {
                        "use": false,
                        "stock": null
                    },
                    "PP": {
                        "use": false,
                        "stock": null
                    },
                    "SP": {
                        "use": false,
                        "stock": null
                    }
                }
            ]
        },
        "ジャンピン・ジェリーフィッシュ": {
            "Realtime": {
                "update_time": "（9:00更新）",
                "wait_time": "5",
                "operation": "運営中",
                "operation_time": "9:00 – 21:00",
                "operation_warning": "",
                "DPA": {
                    "use": false,
                    "stock": null
                },
                "PP": {
                    "use": false,
                    "stock": null
                },
                "SP": {
                    "use": false,
                    "stock": null
                }
            },
            "History": [
                {
                    "time": "09:00",
                    "update_time": "運営/公演予定",
                    "wait_time": "",
                    "operation": "",
                    "operation_time": "9:00 - 21:00",
                    "operation_warning": "",
                    "DPA": {
                        "use": false,
                        "stock": null
                    },
                    "PP": {
                        "use": false,
                        "stock": null
                    },
                    "SP": {
                        "use": false,
                        "stock": null
                    }
                },
                {
                    "time": "09:05",
                    "update_time": "（9:00更新）",
                    "wait_time": "5",
                    "operation": "運営中",
                    "operation_time": "9:00 – 21:00",
                    "operation_warning": "",
                    "DPA": {
                        "use": false,
                        "stock": null
                    },
                    "PP": {
                        "use": false,
                        "stock": null
                    },
                    "SP": {
                        "use": false,
                        "stock": null
                    }
                }
            ]
        },
        "スカットルのスクーター": {
            "Realtime": {
                "update_time": "（9:02更新）",
                "wait_time": "5",
                "operation": "運営中",
                "operation_time": "9:00 – 21:00",
                "operation_warning": "",
                "DPA": {
                    "use": false,
                    "stock": null
                },
                "PP": {
                    "use": false,
                    "stock": null
                },
                "SP": {
                    "use": false,
                    "stock": null
                }
            },
            "History": [
                {
                    "time": "09:00",
                    "update_time": "運営/公演予定",
                    "wait_time": "",
                    "operation": "",
                    "operation_time": "9:00 - 21:00",
                    "operation_warning": "",
                    "DPA": {
                        "use": false,
                        "stock": null
                    },
                    "PP": {
                        "use": false,
                        "stock": null
                    },
                    "SP": {
                        "use": false,
                        "stock": null
                    }
                },
                {
                    "time": "09:05",
                    "update_time": "（9:02更新）",
                    "wait_time": "5",
                    "operation": "運営中",
                    "operation_time": "9:00 – 21:00",
                    "operation_warning": "",
                    "DPA": {
                        "use": false,
                        "stock": null
                    },
                    "PP": {
                        "use": false,
                        "stock": null
                    },
                    "SP": {
                        "use": false,
                        "stock": null
                    }
                }
            ]
        },
        "フランダーのフライングフィッシュコースター": {
            "Realtime": {
                "update_time": "（8:56更新）",
                "wait_time": "",
                "operation": "一時運営中止",
                "operation_time": "9:00 – 21:00",
                "operation_warning": "",
                "DPA": {
                    "use": false,
                    "stock": null
                },
                "PP": {
                    "use": false,
                    "stock": null
                },
                "SP": {
                    "use": false,
                    "stock": null
                }
            },
            "History": [
                {
                    "time": "09:00",
                    "update_time": "運営/公演予定",
                    "wait_time": "",
                    "operation": "",
                    "operation_time": "9:00 - 21:00",
                    "operation_warning": "",
                    "DPA": {
                        "use": false,
                        "stock": null
                    },
                    "PP": {
                        "use": false,
                        "stock": null
                    },
                    "SP": {
                        "use": false,
                        "stock": null
                    }
                },
                {
                    "time": "09:05",
                    "update_time": "（8:56更新）",
                    "wait_time": "",
                    "operation": "一時運営中止",
                    "operation_time": "9:00 – 21:00",
                    "operation_warning": "",
                    "DPA": {
                        "use": false,
                        "stock": null
                    },
                    "PP": {
                        "use": false,
                        "stock": null
                    },
                    "SP": {
                        "use": false,
                        "stock": null
                    }
                }
            ]
        },
        "ブローフィッシュ・バルーンレース": {
            "Realtime": {
                "update_time": "（9:01更新）",
                "wait_time": "5",
                "operation": "運営中",
                "operation_time": "9:00 – 21:00",
                "operation_warning": "",
                "DPA": {
                    "use": false,
                    "stock": null
                },
                "PP": {
                    "use": false,
                    "stock": null
                },
                "SP": {
                    "use": false,
                    "stock": null
                }
            },
            "History": [
                {
                    "time": "09:00",
                    "update_time": "運営/公演予定",
                    "wait_time": "",
                    "operation": "",
                    "operation_time": "9:00 - 21:00",
                    "operation_warning": "",
                    "DPA": {
                        "use": false,
                        "stock": null
                    },
                    "PP": {
                        "use": false,
                        "stock": null
                    },
                    "SP": {
                        "use": false,
                        "stock": null
                    }
                },
                {
                    "time": "09:05",
                    "update_time": "（9:01更新）",
                    "wait_time": "5",
                    "operation": "運営中",
                    "operation_time": "9:00 – 21:00",
                    "operation_warning": "",
                    "DPA": {
                        "use": false,
                        "stock": null
                    },
                    "PP": {
                        "use": false,
                        "stock": null
                    },
                    "SP": {
                        "use": false,
                        "stock": null
                    }
                }
            ]
        },
        "マーメイドラグーンシアター": {
            "Realtime": {
                "update_time": "（9:00更新）",
                "wait_time": "",
                "operation": "運営・公演中止",
                "operation_time": "",
                "operation_warning": "",
                "DPA": {
                    "use": false,
                    "stock": null
                },
                "PP": {
                    "use": false,
                    "stock": null
                },
                "SP": {
                    "use": false,
                    "stock": null
                }
            },
            "History": [
                {
                    "time": "09:00",
                    "update_time": "運営/公演予定",
                    "wait_time": "",
                    "operation": "",
                    "operation_time": "ー",
                    "operation_warning": "",
                    "DPA": {
                        "use": false,
                        "stock": null
                    },
                    "PP": {
                        "use": false,
                        "stock": null
                    },
                    "SP": {
                        "use": false,
                        "stock": null
                    }
                }
            ]
        },
        "ワールプール": {
            "Realtime": {
                "update_time": "（9:00更新）",
                "wait_time": "5",
                "operation": "運営中",
                "operation_time": "9:00 – 21:00",
                "operation_warning": "",
                "DPA": {
                    "use": false,
                    "stock": null
                },
                "PP": {
                    "use": false,
                    "stock": null
                },
                "SP": {
                    "use": false,
                    "stock": null
                }
            },
            "History": [
                {
                    "time": "09:00",
                    "update_time": "運営/公演予定",
                    "wait_time": "",
                    "operation": "",
                    "operation_time": "9:00 - 21:00",
                    "operation_warning": "",
                    "DPA": {
                        "use": false,
                        "stock": null
                    },
                    "PP": {
                        "use": false,
                        "stock": null
                    },
                    "SP": {
                        "use": false,
                        "stock": null
                    }
                },
                {
                    "time": "09:05",
                    "update_time": "（9:00更新）",
                    "wait_time": "5",
                    "operation": "運営中",
                    "operation_time": "9:00 – 21:00",
                    "operation_warning": "",
                    "DPA": {
                        "use": false,
                        "stock": null
                    },
                    "PP": {
                        "use": false,
                        "stock": null
                    },
                    "SP": {
                        "use": false,
                        "stock": null
                    }
                }
            ]
        }
    },
    "ミステリアスアイランド": {
        "海底2万マイル": {
            "Realtime": {
                "update_time": "（7:36更新）",
                "wait_time": "",
                "operation": "運営・公演中止",
                "operation_time": "",
                "operation_warning": "",
                "DPA": {
                    "use": false,
                    "stock": null
                },
                "PP": {
                    "use": true,
                    "stock": false
                },
                "SP": {
                    "use": false,
                    "stock": null
                }
            },
            "History": [
                {
                    "time": "09:00",
                    "update_time": "運営/公演予定",
                    "wait_time": "",
                    "operation": "",
                    "operation_time": "ー",
                    "operation_warning": "",
                    "DPA": {
                        "use": false,
                        "stock": null
                    },
                    "PP": {
                        "use": true,
                        "stock": false
                    },
                    "SP": {
                        "use": false,
                        "stock": null
                    }
                }
            ]
        },
        "センター・オブ・ジ・アース": {
            "Realtime": {
                "update_time": "（9:00更新）",
                "wait_time": "5",
                "operation": "運営中",
                "operation_time": "9:00 – 21:00",
                "operation_warning": "ディズニー・プレミアアクセス販売中",
                "DPA": {
                    "use": true,
                    "stock": true
                },
                "PP": {
                    "use": false,
                    "stock": null
                },
                "SP": {
                    "use": false,
                    "stock": null
                }
            },
            "History": [
                {
                    "time": "09:00",
                    "update_time": "運営/公演予定",
                    "wait_time": "",
                    "operation": "",
                    "operation_time": "9:00 - 21:00",
                    "operation_warning": "",
                    "DPA": {
                        "use": true,
                        "stock": false
                    },
                    "PP": {
                        "use": false,
                        "stock": null
                    },
                    "SP": {
                        "use": false,
                        "stock": null
                    }
                },
                {
                    "time": "09:05",
                    "update_time": "（9:00更新）",
                    "wait_time": "5",
                    "operation": "運営中",
                    "operation_time": "9:00 – 21:00",
                    "operation_warning": "ディズニー・プレミアアクセス販売中",
                    "DPA": {
                        "use": true,
                        "stock": true
                    },
                    "PP": {
                        "use": false,
                        "stock": null
                    },
                    "SP": {
                        "use": false,
                        "stock": null
                    }
                }
            ]
        }
    }
}